ai_commit/__init__.py
ai_commit/cli.py
ai_commit/generator.py
ai_commit/git.py
ai_commit/settings.py
qommit-0.1.0.dist-info/METADATA
qommit-0.1.0.dist-info/WHEEL
qommit-0.1.0.dist-info/entry_points.txt
qommit-0.1.0.dist-info/RECORD
