Metadata-Version: 2.4
Name: qommit
Version: 0.1.0
Summary: AI-powered git commit message generator using PydanticAI
Requires-Python: >=3.10
Requires-Dist: click>=8.0.0
Requires-Dist: platformdirs>=4.0.0
Requires-Dist: pydantic-ai>=0.0.30
Requires-Dist: pyyaml>=6.0.0
Provides-Extra: dev
Requires-Dist: pyright>=1.1.0; extra == 'dev'
Requires-Dist: pytest-asyncio>=0.24.0; extra == 'dev'
Requires-Dist: pytest>=8.0.0; extra == 'dev'
